MANIFEST.in
README.md
setup.py
chipy/Chipy.py
chipy/__init__.py
chipy.egg-info/PKG-INFO
chipy.egg-info/SOURCES.txt
chipy.egg-info/dependency_links.txt
chipy.egg-info/top_level.txt