Metadata-Version: 1.0
Name: chipy
Version: 0.1.1
Summary: Chipy is a single-file python module for generating digital hardware.
Home-page: https://github.com/chipy-hdl/chipy
Author: Clifford Wolf
Author-email: clifford@clifford.at
License: ISC
Keywords: eda,cad,hdl,verilog
Platform: UNKNOWN
